{
    "name": "Cinccino",
    "national_no": "0573",
    "type": [
        "Normal"
    ],
    "species": "Scarf Pok\u00e9mon",
    "height": "0.5\u00a0m (1\u203208\u2033)",
    "weight": "7.5\u00a0kg (16.5\u00a0lbs)",
    "abilities": [
        "Cute Charm",
        "Technician",
        "Skill Link"
    ],
    "ev_yield": "\n2 Speed ",
    "catch_rate": "\n60 ",
    "base_happiness": "\n50 ",
    "base_exp": "165",
    "growth_rate": "Fast",
    "egg_groups": [
        "Field"
    ],
    "gender_ratio": [
        "25% male",
        "75% female"
    ],
    "egg_cycle": "15 (3,599\u20133,855 steps)",
    "stats": {
        "hp": "75",
        "attack": "95",
        "defense": "60",
        "sp. atk": "65",
        "sp. def": "60",
        "speed": "115",
        "total": "470"
    },
    "evolution_chain": [
        "Minccino",
        "Cinccino"
    ],
    "pokedex_entries": {
        "Black": "Their white fur is coated in a special oil that makes it easy for them to deflect attacks.",
        "White": "Their white fur feels amazing to touch. Their fur repels dust and prevents static electricity from building up.",
        "Black 2 / White 2": "Cinccino\u2019s body is coated in a special oil that helps it deflect attacks, such as punches.",
        "X / Omega Ruby": "Their white fur feels amazing to touch. Their fur repels dust and prevents static electricity from building up.",
        "Y / Alpha Sapphire": "Cinccino\u2019s body is coated in a special oil that helps it deflect attacks, such as punches.",
        "Ultra Sun": "The white parts of its coat are covered in an oil secreted from its body, so this Pok\u00e9mon can slide right away from its enemies\u2019 attacks.",
        "Ultra Moon": "The oil that seeps from its body is really smooth. For people troubled by bad skin, this oil is an effective treatment.",
        "Sword": "Its body secretes oil that this Pok\u00e9mon spreads over its nest as a coating to protect it from dust. Cinccino won\u2019t tolerate even a speck of the stuff.",
        "Shield": "A special oil that seeps through their fur helps them avoid attacks. The oil fetches a high price at market."
    },
    "moves_levelup": [
        {
            "level": "1",
            "move": "Bullet Seed",
            "type": "Grass",
            "category": "Physical",
            "power": "25",
            "accuracy": "100"
        },
        {
            "level": "1",
            "move": "Charm",
            "type": "Fairy",
            "category": "Status",
            "power": "\u2014",
            "accuracy": "100"
        },
        {
            "level": "1",
            "move": "Pound",
            "type": "Normal",
            "category": "Physical",
            "power": "40",
            "accuracy": "100"
        },
        {
            "level": "1",
            "move": "Sing",
            "type": "Normal",
            "category": "Status",
            "power": "\u2014",
            "accuracy": "55"
        },
        {
            "level": "1",
            "move": "After You",
            "type": "Normal",
            "category": "Status",
            "power": "\u2014",
            "accuracy": "\u2014"
        },
        {
            "level": "1",
            "move": "Baby-Doll Eyes",
            "type": "Fairy",
            "category": "Status",
            "power": "\u2014",
            "accuracy": "100"
        },
        {
            "level": "1",
            "move": "Bullet Seed",
            "type": "Grass",
            "category": "Physical",
            "power": "25",
            "accuracy": "100"
        },
        {
            "level": "1",
            "move": "Charm",
            "type": "Fairy",
            "category": "Status",
            "power": "\u2014",
            "accuracy": "100"
        },
        {
            "level": "1",
            "move": "Echoed Voice",
            "type": "Normal",
            "category": "Special",
            "power": "40",
            "accuracy": "100"
        },
        {
            "level": "1",
            "move": "Encore",
            "type": "Normal",
            "category": "Status",
            "power": "\u2014",
            "accuracy": "100"
        },
        {
            "level": "1",
            "move": "Helping Hand",
            "type": "Normal",
            "category": "Status",
            "power": "\u2014",
            "accuracy": "\u2014"
        },
        {
            "level": "1",
            "move": "Hyper Voice",
            "type": "Normal",
            "category": "Special",
            "power": "90",
            "accuracy": "100"
        },
        {
            "level": "1",
            "move": "Last Resort",
            "type": "Normal",
            "category": "Physical",
            "power": "140",
            "accuracy": "100"
        },
        {
            "level": "1",
            "move": "Pound",
            "type": "Normal",
            "category": "Physical",
            "power": "40",
            "accuracy": "100"
        },
        {
            "level": "1",
            "move": "Rock Blast",
            "type": "Rock",
            "category": "Physical",
            "power": "25",
            "accuracy": "90"
        },
        {
            "level": "1",
            "move": "Sing",
            "type": "Normal",
            "category": "Status",
            "power": "\u2014",
            "accuracy": "55"
        },
        {
            "level": "1",
            "move": "Slam",
            "type": "Normal",
            "category": "Physical",
            "power": "80",
            "accuracy": "75"
        },
        {
            "level": "1",
            "move": "Swift",
            "type": "Normal",
            "category": "Special",
            "power": "60",
            "accuracy": "\u221e"
        },
        {
            "level": "1",
            "move": "Tail Slap",
            "type": "Normal",
            "category": "Physical",
            "power": "25",
            "accuracy": "85"
        },
        {
            "level": "1",
            "move": "Tickle",
            "type": "Normal",
            "category": "Status",
            "power": "\u2014",
            "accuracy": "100"
        }
    ],
    "moves_tm": [
        {
            "tm": "TM01",
            "move": "Take Down",
            "type": "Normal",
            "category": "Physical",
            "power": "90",
            "accuracy": "85"
        },
        {
            "tm": "TM02",
            "move": "Charm",
            "type": "Fairy",
            "category": "Status",
            "power": "\u2014",
            "accuracy": "100"
        },
        {
            "tm": "TM03",
            "move": "Fake Tears",
            "type": "Dark",
            "category": "Status",
            "power": "\u2014",
            "accuracy": "100"
        },
        {
            "tm": "TM05",
            "move": "Mud-Slap",
            "type": "Ground",
            "category": "Special",
            "power": "20",
            "accuracy": "100"
        },
        {
            "tm": "TM07",
            "move": "Protect",
            "type": "Normal",
            "category": "Status",
            "power": "\u2014",
            "accuracy": "\u2014"
        },
        {
            "tm": "TM18",
            "move": "Thief",
            "type": "Dark",
            "category": "Physical",
            "power": "60",
            "accuracy": "100"
        },
        {
            "tm": "TM20",
            "move": "Trailblaze",
            "type": "Grass",
            "category": "Physical",
            "power": "50",
            "accuracy": "100"
        },
        {
            "tm": "TM22",
            "move": "Chilling Water",
            "type": "Water",
            "category": "Special",
            "power": "50",
            "accuracy": "100"
        },
        {
            "tm": "TM25",
            "move": "Facade",
            "type": "Normal",
            "category": "Physical",
            "power": "70",
            "accuracy": "100"
        },
        {
            "tm": "TM32",
            "move": "Swift",
            "type": "Normal",
            "category": "Special",
            "power": "60",
            "accuracy": "\u221e"
        },
        {
            "tm": "TM43",
            "move": "Fling",
            "type": "Dark",
            "category": "Physical",
            "power": "\u2014",
            "accuracy": "100"
        },
        {
            "tm": "TM47",
            "move": "Endure",
            "type": "Normal",
            "category": "Status",
            "power": "\u2014",
            "accuracy": "\u2014"
        },
        {
            "tm": "TM49",
            "move": "Sunny Day",
            "type": "Fire",
            "category": "Status",
            "power": "\u2014",
            "accuracy": "\u2014"
        },
        {
            "tm": "TM50",
            "move": "Rain Dance",
            "type": "Water",
            "category": "Status",
            "power": "\u2014",
            "accuracy": "\u2014"
        },
        {
            "tm": "TM55",
            "move": "Dig",
            "type": "Ground",
            "category": "Physical",
            "power": "80",
            "accuracy": "100"
        },
        {
            "tm": "TM56",
            "move": "Bullet Seed",
            "type": "Grass",
            "category": "Physical",
            "power": "25",
            "accuracy": "100"
        },
        {
            "tm": "TM60",
            "move": "U-turn",
            "type": "Bug",
            "category": "Physical",
            "power": "70",
            "accuracy": "100"
        },
        {
            "tm": "TM70",
            "move": "Sleep Talk",
            "type": "Normal",
            "category": "Status",
            "power": "\u2014",
            "accuracy": "\u2014"
        },
        {
            "tm": "TM71",
            "move": "Seed Bomb",
            "type": "Grass",
            "category": "Physical",
            "power": "80",
            "accuracy": "100"
        },
        {
            "tm": "TM75",
            "move": "Light Screen",
            "type": "Psychic",
            "category": "Status",
            "power": "\u2014",
            "accuracy": "\u2014"
        },
        {
            "tm": "TM76",
            "move": "Rock Blast",
            "type": "Rock",
            "category": "Physical",
            "power": "25",
            "accuracy": "90"
        },
        {
            "tm": "TM79",
            "move": "Dazzling Gleam",
            "type": "Fairy",
            "category": "Special",
            "power": "80",
            "accuracy": "100"
        },
        {
            "tm": "TM81",
            "move": "Grass Knot",
            "type": "Grass",
            "category": "Special",
            "power": "\u2014",
            "accuracy": "100"
        },
        {
            "tm": "TM82",
            "move": "Thunder Wave",
            "type": "Electric",
            "category": "Status",
            "power": "\u2014",
            "accuracy": "90"
        },
        {
            "tm": "TM85",
            "move": "Rest",
            "type": "Psychic",
            "category": "Status",
            "power": "\u2014",
            "accuracy": "\u2014"
        },
        {
            "tm": "TM102",
            "move": "Gunk Shot",
            "type": "Poison",
            "category": "Physical",
            "power": "120",
            "accuracy": "80"
        },
        {
            "tm": "TM103",
            "move": "Substitute",
            "type": "Normal",
            "category": "Status",
            "power": "\u2014",
            "accuracy": "\u2014"
        },
        {
            "tm": "TM117",
            "move": "Hyper Voice",
            "type": "Normal",
            "category": "Special",
            "power": "90",
            "accuracy": "100"
        },
        {
            "tm": "TM122",
            "move": "Encore",
            "type": "Normal",
            "category": "Status",
            "power": "\u2014",
            "accuracy": "100"
        },
        {
            "tm": "TM124",
            "move": "Ice Spinner",
            "type": "Ice",
            "category": "Physical",
            "power": "80",
            "accuracy": "100"
        },
        {
            "tm": "TM126",
            "move": "Thunderbolt",
            "type": "Electric",
            "category": "Special",
            "power": "90",
            "accuracy": "100"
        },
        {
            "tm": "TM127",
            "move": "Play Rough",
            "type": "Fairy",
            "category": "Physical",
            "power": "90",
            "accuracy": "90"
        },
        {
            "tm": "TM129",
            "move": "Calm Mind",
            "type": "Psychic",
            "category": "Status",
            "power": "\u2014",
            "accuracy": "\u2014"
        },
        {
            "tm": "TM130",
            "move": "Helping Hand",
            "type": "Normal",
            "category": "Status",
            "power": "\u2014",
            "accuracy": "\u2014"
        },
        {
            "tm": "TM132",
            "move": "Baton Pass",
            "type": "Normal",
            "category": "Status",
            "power": "\u2014",
            "accuracy": "\u2014"
        },
        {
            "tm": "TM152",
            "move": "Giga Impact",
            "type": "Normal",
            "category": "Physical",
            "power": "150",
            "accuracy": "90"
        },
        {
            "tm": "TM158",
            "move": "Focus Blast",
            "type": "Fighting",
            "category": "Special",
            "power": "120",
            "accuracy": "70"
        },
        {
            "tm": "TM163",
            "move": "Hyper Beam",
            "type": "Normal",
            "category": "Special",
            "power": "150",
            "accuracy": "90"
        },
        {
            "tm": "TM166",
            "move": "Thunder",
            "type": "Electric",
            "category": "Special",
            "power": "110",
            "accuracy": "70"
        },
        {
            "tm": "TM171",
            "move": "Tera Blast",
            "type": "Normal",
            "category": "Special",
            "power": "80",
            "accuracy": "100"
        },
        {
            "tm": "TM181",
            "move": "Knock Off",
            "type": "Dark",
            "category": "Physical",
            "power": "65",
            "accuracy": "100"
        },
        {
            "tm": "TM183",
            "move": "Super Fang",
            "type": "Normal",
            "category": "Physical",
            "power": "\u2014",
            "accuracy": "90"
        },
        {
            "tm": "TM191",
            "move": "Uproar",
            "type": "Normal",
            "category": "Special",
            "power": "90",
            "accuracy": "100"
        },
        {
            "tm": "TM204",
            "move": "Double-Edge",
            "type": "Normal",
            "category": "Physical",
            "power": "120",
            "accuracy": "100"
        },
        {
            "tm": "TM205",
            "move": "Endeavor",
            "type": "Normal",
            "category": "Physical",
            "power": "\u2014",
            "accuracy": "100"
        },
        {
            "tm": "TM212",
            "move": "Triple Axel",
            "type": "Ice",
            "category": "Physical",
            "power": "20",
            "accuracy": "90"
        },
        {
            "tm": "TM227",
            "move": "Alluring Voice",
            "type": "Fairy",
            "category": "Special",
            "power": "80",
            "accuracy": "100"
        },
        {
            "tm": "TM08",
            "move": "Hyper Beam",
            "type": "Normal",
            "category": "Special",
            "power": "150",
            "accuracy": "90"
        },
        {
            "tm": "TM09",
            "move": "Giga Impact",
            "type": "Normal",
            "category": "Physical",
            "power": "150",
            "accuracy": "90"
        },
        {
            "tm": "TM14",
            "move": "Thunder Wave",
            "type": "Electric",
            "category": "Status",
            "power": "\u2014",
            "accuracy": "90"
        },
        {
            "tm": "TM15",
            "move": "Dig",
            "type": "Ground",
            "category": "Physical",
            "power": "80",
            "accuracy": "100"
        },
        {
            "tm": "TM17",
            "move": "Light Screen",
            "type": "Psychic",
            "category": "Status",
            "power": "\u2014",
            "accuracy": "\u2014"
        },
        {
            "tm": "TM19",
            "move": "Safeguard",
            "type": "Normal",
            "category": "Status",
            "power": "\u2014",
            "accuracy": "\u2014"
        },
        {
            "tm": "TM21",
            "move": "Rest",
            "type": "Psychic",
            "category": "Status",
            "power": "\u2014",
            "accuracy": "\u2014"
        },
        {
            "tm": "TM23",
            "move": "Thief",
            "type": "Dark",
            "category": "Physical",
            "power": "60",
            "accuracy": "100"
        },
        {
            "tm": "TM24",
            "move": "Snore",
            "type": "Normal",
            "category": "Special",
            "power": "50",
            "accuracy": "100"
        },
        {
            "tm": "TM25",
            "move": "Protect",
            "type": "Normal",
            "category": "Status",
            "power": "\u2014",
            "accuracy": "\u2014"
        },
        {
            "tm": "TM29",
            "move": "Charm",
            "type": "Fairy",
            "category": "Status",
            "power": "\u2014",
            "accuracy": "100"
        },
        {
            "tm": "TM31",
            "move": "Attract",
            "type": "Normal",
            "category": "Status",
            "power": "\u2014",
            "accuracy": "100"
        },
        {
            "tm": "TM33",
            "move": "Rain Dance",
            "type": "Water",
            "category": "Status",
            "power": "\u2014",
            "accuracy": "\u2014"
        },
        {
            "tm": "TM34",
            "move": "Sunny Day",
            "type": "Fire",
            "category": "Status",
            "power": "\u2014",
            "accuracy": "\u2014"
        },
        {
            "tm": "TM39",
            "move": "Facade",
            "type": "Normal",
            "category": "Physical",
            "power": "70",
            "accuracy": "100"
        },
        {
            "tm": "TM40",
            "move": "Swift",
            "type": "Normal",
            "category": "Special",
            "power": "60",
            "accuracy": "\u221e"
        },
        {
            "tm": "TM41",
            "move": "Helping Hand",
            "type": "Normal",
            "category": "Status",
            "power": "\u2014",
            "accuracy": "\u2014"
        },
        {
            "tm": "TM47",
            "move": "Fake Tears",
            "type": "Dark",
            "category": "Status",
            "power": "\u2014",
            "accuracy": "100"
        },
        {
            "tm": "TM50",
            "move": "Bullet Seed",
            "type": "Grass",
            "category": "Physical",
            "power": "25",
            "accuracy": "100"
        },
        {
            "tm": "TM54",
            "move": "Rock Blast",
            "type": "Rock",
            "category": "Physical",
            "power": "25",
            "accuracy": "90"
        },
        {
            "tm": "TM56",
            "move": "U-turn",
            "type": "Bug",
            "category": "Physical",
            "power": "70",
            "accuracy": "100"
        },
        {
            "tm": "TM59",
            "move": "Fling",
            "type": "Dark",
            "category": "Physical",
            "power": "\u2014",
            "accuracy": "100"
        },
        {
            "tm": "TM76",
            "move": "Round",
            "type": "Normal",
            "category": "Special",
            "power": "60",
            "accuracy": "100"
        },
        {
            "tm": "TM79",
            "move": "Retaliate",
            "type": "Normal",
            "category": "Physical",
            "power": "70",
            "accuracy": "100"
        },
        {
            "tm": "TM84",
            "move": "Tail Slap",
            "type": "Normal",
            "category": "Physical",
            "power": "25",
            "accuracy": "85"
        }
    ],
    "moves_egg": [
        {
            "move": "Aqua Tail",
            "type": "Water",
            "category": "Physical",
            "power": "90",
            "accuracy": "90"
        },
        {
            "move": "Flail",
            "type": "Normal",
            "category": "Physical",
            "power": "\u2014",
            "accuracy": "100"
        },
        {
            "move": "Knock Off",
            "type": "Dark",
            "category": "Physical",
            "power": "65",
            "accuracy": "100"
        },
        {
            "move": "Tail Whip",
            "type": "Normal",
            "category": "Status",
            "power": "\u2014",
            "accuracy": "100"
        }
    ],
    "location": {
        "Black / White": "Route 5",
        "Black 2 / White 2": "Route 5",
        "X / Y": "Trade/migrate from another game",
        "Omega Ruby / Alpha Sapphire": "Minccino",
        "Sun / Moon": "Trade/migrate from another game",
        "Ultra Sun / Ultra Moon": "Minccino",
        "Let's Go Pikachu / Let's Go Eevee": "Not available in this game",
        "Sword / Shield": "Minccino",
        "Brilliant Diamond / Shining Pearl / Legends: Arceus": "Not available in this game",
        "Scarlet / Violet": "Location data not yet available"
    },
    "other_languages": {
        "English": "Cinccino",
        "Japanese": "\u30c1\u30e9\u30c1\u30fc\u30ce (Chillaccino)",
        "German": "Chillabell",
        "French": "Pashmilla",
        "Italian": "Cinccino",
        "Spanish": "Cinccino",
        "Korean": "\uce58\ub77c\uce58\ub178 (chirachino)",
        "Chinese (Simplified)": "\u5947\u8bfa\u6817\u9f20",
        "Chinese (Traditional)": "\u5947\u8afe\u6817\u9f20"
    }
}